arceus/__init__.py
arceus/__main__.py
arceus/account.py
arceus/benchmark.py
arceus/cli.py
arceus/logger.py
arceus/snipers.py
arceus-2.1.4.dist-info/METADATA
arceus-2.1.4.dist-info/WHEEL
arceus-2.1.4.dist-info/entry_points.txt
arceus-2.1.4.dist-info/top_level.txt
arceus-2.1.4.dist-info/RECORD
