Metadata-Version: 2.1
Name: arceus
Version: 2.1.4
Summary: Minecraft name sniper.
Home-page: UNKNOWN
Author: Aquild
License: UNKNOWN
Platform: UNKNOWN
Classifier: Programming Language :: Python
Classifier: Programming Language :: Python :: 3.8
Requires-Dist: arceus-net
Requires-Dist: requests
Requires-Dist: requests-random-user-agent
Requires-Dist: tcp-latency
Requires-Dist: bs4
Requires-Dist: pause
Requires-Dist: click
Requires-Dist: PyInquirer
Requires-Dist: colorama
Requires-Dist: termcolor
Requires-Dist: pyfiglet
